Workbook

Sheet Premissas
A1: BLACK FRIDAY 2026 — PONTO DE EQUILÍBRIO
A2: Centro Cultural Hugo de São Vítor · Professor Robson Cardenas · outubro e novembro de 2026
A4: Edite apenas as células AZUIS sobre fundo amarelo. Todo o resto é fórmula.
A6: EQUIPE E FERRAMENTAS — custo mensal
A7: Nayara — social media | B7: 1000
A8: Henri — copy | B8: 2000
A9: Designer / webdesigner | B9: 2000
A10: Gestor de tráfego | B10: 2000
A11: Infra | B11: 800
A12: Ferramentas — e-mail, ManyChat, disparos | B12: 2000
A13: Editor de vídeo | B13: 1500
A14: TOTAL POR MÊS | B14: =SUM(B7:B13)
A16: CAMPANHA
A17: Meses de equipe (outubro e novembro) | B17: 2
A18: Verba de tráfego — total da campanha | B18: 5000
A19: CUSTO TOTAL DA CAMPANHA | B19: =B14*B17+B18
A21: TAXAS E PERDAS
A22: Hotmart — percentual por venda | B22: 0.099
A23: Hotmart — valor fixo por venda | B23: 1
A24: Reembolso estimado | B24: 0.05
A25: Imposto sobre faturamento | B25: 0
A27: PREÇOS
A28: Preço — não aluno | B28: 1997
A29: Preço — aluno | B29: 1497
A30: Líquido por venda — não aluno | B30: =(B28*(1-$B$22)-$B$23)*(1-$B$24)*(1-$B$25)
A31: Líquido por venda — aluno | B31: =(B29*(1-$B$22)-$B$23)*(1-$B$24)*(1-$B$25)
A33: MIX ESPERADO DE VENDAS
A34: Proporção — alunos | B34: 2
A35: Proporção — não alunos | B35: 1
A36: Líquido médio por venda no mix | B36: =(B34*B31+B35*B30)/(B34+B35)
A38: DIVISÃO DO RESULTADO
A39: Kalinne / Brand | B39: 0.5
A40: Robson / Centro | B40: 0.5
A42: MODELO ANTIGO — só para comparar
A43: Comissão da Brand sobre o faturamento | B43: 0.2
A44: Time da Brand — custo mensal | B44: =B7+B8+B9+B13
A45: Time da Brand — custo na campanha | B45: =B44*B17
A47: Números que vieram de você, e não de mim: todos os custos de equipe e ferramentas, e a verba de tráfego.
A48: Números que eu arbitrei e você precisa confirmar: taxa da Hotmart, reembolso, imposto. Estão com comentário na célula.

Sheet Ponto de Equilibrio
A1: QUANTAS VENDAS PARA EMPATAR
A2: Vendas necessárias para a receita líquida cobrir o custo total da campanha.
A4: O CUSTO
A5: Equipe e ferramentas (2 meses) | B5: =Premissas!$B$14*Premissas!$B$17
A6: Tráfego | B6: =Premissas!$B$18
A7: CUSTO TOTAL | B7: =Premissas!$B$19
A9: VENDAS PARA EMPATAR
A10: Só com vendas a preço de não aluno | B10: =ROUNDUP(B7/Premissas!$B$30,0)
A11: Só com vendas a preço de aluno | B11: =ROUNDUP(B7/Premissas!$B$31,0)
A12: No mix esperado | B12: =ROUNDUP(B7/Premissas!$B$36,0)
A14: Referência: o lançamento de setembro de 2026 vendeu cerca de 21 unidades.
A16: E SE A VERBA DE TRÁFEGO FOR OUTRA
A17: Verba de tráfego | B17: Custo total | C17: Vendas p/ empatar | D17: A mais que sem tráfego
A18: 0 | B18: =Premissas!$B$14*Premissas!$B$17+A18 | C18: =ROUNDUP(B18/Premissas!$B$36,0) | D18: =C18-$C$18
A19: 5000 | B19: =Premissas!$B$14*Premissas!$B$17+A19 | C19: =ROUNDUP(B19/Premissas!$B$36,0) | D19: =C19-$C$18
A20: 10000 | B20: =Premissas!$B$14*Premissas!$B$17+A20 | C20: =ROUNDUP(B20/Premissas!$B$36,0) | D20: =C20-$C$18
A21: 15000 | B21: =Premissas!$B$14*Premissas!$B$17+A21 | C21: =ROUNDUP(B21/Premissas!$B$36,0) | D21: =C21-$C$18
A25: O TRÁFEGO SE PAGA?
A26: Vendas que a verba de tráfego exige só para se pagar | B26: =ROUNDUP(Premissas!$B$18/Premissas!$B$36,0)
A27: Custo por venda no tráfego de setembro (R$ 12.891 / 4) | B27: =12891/4
A28: Receita líquida de uma venda a preço de não aluno | B28: =Premissas!$B$30
A29: Em setembro, cada venda trazida por tráfego custou quase o dobro do que ela rende.

Sheet Simulador
A1: SIMULADOR
A2: Digite as duas células azuis. Tudo abaixo recalcula.
A4: VENDAS
A5: Vendas para alunos | B5: 40
A6: Vendas para não alunos | B6: 25
A7: TOTAL DE VENDAS | B7: =B5+B6
A9: RESULTADO
A10: Faturamento bruto | B10: =B5*Premissas!$B$29+B6*Premissas!$B$28
A11: (-) Hotmart | B11: =-(B10*Premissas!$B$22+B7*Premissas!$B$23)
A12: (-) Reembolso | B12: =-(B10+B11)*Premissas!$B$24
A13: (-) Imposto | B13: =-(B10+B11+B12)*Premissas!$B$25
A14: RECEITA LÍQUIDA | B14: =B10+B11+B12+B13
A15: (-) Custo total da campanha | B15: =-Premissas!$B$19
A16: LUCRO | B16: =B14+B15
A18: DIVISÃO
A19: Kalinne / Brand | B19: =B16*Premissas!$B$39
A20: Robson / Centro | B20: =B16*Premissas!$B$40
A22: CONFERÊNCIA
A23: Falta quanto para empatar | B23: =IF(B16>=0,0,-B16)
A24: Vendas que ainda faltam para empatar | B24: =IF(B16>=0,0,ROUNDUP(-B16/Premissas!$B$36,0))
A25: Margem sobre o faturamento | B25: =IF(B10=0,0,B16/B10)

Sheet Cenarios
A1: TRÊS CENÁRIOS
A2: As quatro linhas azuis são as suposições de volume. Mude à vontade.
B4: Conservador | C4: Base | D4: Bom
A5: Vendas para alunos | B5: 22 | C5: 40 | D5: 60
A6: Vendas para não alunos | B6: 12 | C6: 25 | D6: 45
A7: Total de vendas | B7: =B5+B6 | C7: =C5+C6 | D7: =D5+D6
A8: Faturamento bruto | B8: =B5*Premissas!$B$29+B6*Premissas!$B$28 | C8: =C5*Premissas!$B$29+C6*Premissas!$B$28 | D8: =D5*Premissas!$B$29+D6*Premissas!$B$28
A9: Receita líquida | B9: =B5*Premissas!$B$31+B6*Premissas!$B$30 | C9: =C5*Premissas!$B$31+C6*Premissas!$B$30 | D9: =D5*Premissas!$B$31+D6*Premissas!$B$30
A10: Custo total | B10: =Premissas!$B$19 | C10: =Premissas!$B$19 | D10: =Premissas!$B$19
A11: LUCRO | B11: =B9-B10 | C11: =C9-C10 | D11: =D9-D10
A12: Kalinne / Brand | B12: =B11*Premissas!$B$39 | C12: =C11*Premissas!$B$39 | D12: =D11*Premissas!$B$39
A13: Robson / Centro | B13: =B11*Premissas!$B$40 | C13: =C11*Premissas!$B$40 | D13: =D11*Premissas!$B$40
A14: Margem sobre o faturamento | B14: =IF(B8=0,0,B11/B8) | C14: =IF(C8=0,0,C11/C8) | D14: =IF(D8=0,0,D11/D8)
A16: Conservador = 22 vendas sobre ~750 compradores históricos (2,9%) e 12 vendas de tráfego — o triplo do que setembro entregou.
A17: Os volumes são suposição minha. Não há histórico de Black Friday nesta casa para calibrar.

Sheet Sensibilidade
A1: LUCRO TOTAL POR COMBINAÇÃO DE VENDAS
A2: Linhas: vendas para alunos. Colunas: vendas para não alunos. Verde = lucro.
A4: alunos ↓ não alunos → | B4: 0 | C4: 5 | D4: 10 | E4: 15 | F4: 20 | G4: 25 | H4: 30 | I4: 40 | J4: 50
A5: 0 | B5: =0*Premissas!$B$31+0*Premissas!$B$30-Premissas!$B$19 | C5: =0*Premissas!$B$31+5*Premissas!$B$30-Premissas!$B$19 | D5: =0*Premissas!$B$31+10*Premissas!$B$30-Premissas!$B$19 | E5: =0*Premissas!$B$31+15*Premissas!$B$30-Premissas!$B$19 | F5: =0*Premissas!$B$31+20*Premissas!$B$30-Premissas!$B$19 | G5: =0*Premissas!$B$31+25*Premissas!$B$30-Premissas!$B$19 | H5: =0*Premissas!$B$31+30*Premissas!$B$30-Premissas!$B$19 | I5: =0*Premissas!$B$31+40*Premissas!$B$30-Premissas!$B$19 | J5: =0*Premissas!$B$31+50*Premissas!$B$30-Premissas!$B$19
A6: 10 | B6: =10*Premissas!$B$31+0*Premissas!$B$30-Premissas!$B$19 | C6: =10*Premissas!$B$31+5*Premissas!$B$30-Premissas!$B$19 | D6: =10*Premissas!$B$31+10*Premissas!$B$30-Premissas!$B$19 | E6: =10*Premissas!$B$31+15*Premissas!$B$30-Premissas!$B$19 | F6: =10*Premissas!$B$31+20*Premissas!$B$30-Premissas!$B$19 | G6: =10*Premissas!$B$31+25*Premissas!$B$30-Premissas!$B$19 | H6: =10*Premissas!$B$31+30*Premissas!$B$30-Premissas!$B$19 | I6: =10*Premissas!$B$31+40*Premissas!$B$30-Premissas!$B$19 | J6: =10*Premissas!$B$31+50*Premissas!$B$30-Premissas!$B$19
A7: 20 | B7: =20*Premissas!$B$31+0*Premissas!$B$30-Premissas!$B$19 | C7: =20*Premissas!$B$31+5*Premissas!$B$30-Premissas!$B$19 | D7: =20*Premissas!$B$31+10*Premissas!$B$30-Premissas!$B$19 | E7: =20*Premissas!$B$31+15*Premissas!$B$30-Premissas!$B$19 | F7: =20*Premissas!$B$31+20*Premissas!$B$30-Premissas!$B$19 | G7: =20*Premissas!$B$31+25*Premissas!$B$30-Premissas!$B$19 | H7: =20*Premissas!$B$31+30*Premissas!$B$30-Premissas!$B$19 | I7: =20*Premissas!$B$31+40*Premissas!$B$30-Premissas!$B$19 | J7: =20*Premissas!$B$31+50*Premissas!$B$30-Premissas!$B$19
A8: 30 | B8: =30*Premissas!$B$31+0*Premissas!$B$30-Premissas!$B$19 | C8: =30*Premissas!$B$31+5*Premissas!$B$30-Premissas!$B$19 | D8: =30*Premissas!$B$31+10*Premissas!$B$30-Premissas!$B$19 | E8: =30*Premissas!$B$31+15*Premissas!$B$30-Premissas!$B$19 | F8: =30*Premissas!$B$31+20*Premissas!$B$30-Premissas!$B$19 | G8: =30*Premissas!$B$31+25*Premissas!$B$30-Premissas!$B$19 | H8: =30*Premissas!$B$31+30*Premissas!$B$30-Premissas!$B$19 | I8: =30*Premissas!$B$31+40*Premissas!$B$30-Premissas!$B$19 | J8: =30*Premissas!$B$31+50*Premissas!$B$30-Premissas!$B$19
A9: 40 | B9: =40*Premissas!$B$31+0*Premissas!$B$30-Premissas!$B$19 | C9: =40*Premissas!$B$31+5*Premissas!$B$30-Premissas!$B$19 | D9: =40*Premissas!$B$31+10*Premissas!$B$30-Premissas!$B$19 | E9: =40*Premissas!$B$31+15*Premissas!$B$30-Premissas!$B$19 | F9: =40*Premissas!$B$31+20*Premissas!$B$30-Premissas!$B$19 | G9: =40*Premissas!$B$31+25*Premissas!$B$30-Premissas!$B$19 | H9: =40*Premissas!$B$31+30*Premissas!$B$30-Premissas!$B$19 | I9: =40*Premissas!$B$31+40*Premissas!$B$30-Premissas!$B$19 | J9: =40*Premissas!$B$31+50*Premissas!$B$30-Premissas!$B$19
A10: 50 | B10: =50*Premissas!$B$31+0*Premissas!$B$30-Premissas!$B$19 | C10: =50*Premissas!$B$31+5*Premissas!$B$30-Premissas!$B$19 | D10: =50*Premissas!$B$31+10*Premissas!$B$30-Premissas!$B$19 | E10: =50*Premissas!$B$31+15*Premissas!$B$30-Premissas!$B$19 | F10: =50*Premissas!$B$31+20*Premissas!$B$30-Premissas!$B$19 | G10: =50*Premissas!$B$31+25*Premissas!$B$30-Premissas!$B$19 | H10: =50*Premissas!$B$31+30*Premissas!$B$30-Premissas!$B$19 | I10: =50*Premissas!$B$31+40*Premissas!$B$30-Premissas!$B$19 | J10: =50*Premissas!$B$31+50*Premissas!$B$30-Premissas!$B$19
A11: 60 | B11: =60*Premissas!$B$31+0*Premissas!$B$30-Premissas!$B$19 | C11: =60*Premissas!$B$31+5*Premissas!$B$30-Premissas!$B$19 | D11: =60*Premissas!$B$31+10*Premissas!$B$30-Premissas!$B$19 | E11: =60*Premissas!$B$31+15*Premissas!$B$30-Premissas!$B$19 | F11: =60*Premissas!$B$31+20*Premissas!$B$30-Premissas!$B$19 | G11: =60*Premissas!$B$31+25*Premissas!$B$30-Premissas!$B$19 | H11: =60*Premissas!$B$31+30*Premissas!$B$30-Premissas!$B$19 | I11: =60*Premissas!$B$31+40*Premissas!$B$30-Premissas!$B$19 | J11: =60*Premissas!$B$31+50*Premissas!$B$30-Premissas!$B$19
A12: 70 | B12: =70*Premissas!$B$31+0*Premissas!$B$30-Premissas!$B$19 | C12: =70*Premissas!$B$31+5*Premissas!$B$30-Premissas!$B$19 | D12: =70*Premissas!$B$31+10*Premissas!$B$30-Premissas!$B$19 | E12: =70*Premissas!$B$31+15*Premissas!$B$30-Premissas!$B$19 | F12: =70*Premissas!$B$31+20*Premissas!$B$30-Premissas!$B$19 | G12: =70*Premissas!$B$31+25*Premissas!$B$30-Premissas!$B$19 | H12: =70*Premissas!$B$31+30*Premissas!$B$30-Premissas!$B$19 | I12: =70*Premissas!$B$31+40*Premissas!$B$30-Premissas!$B$19 | J12: =70*Premissas!$B$31+50*Premissas!$B$30-Premissas!$B$19
A13: 80 | B13: =80*Premissas!$B$31+0*Premissas!$B$30-Premissas!$B$19 | C13: =80*Premissas!$B$31+5*Premissas!$B$30-Premissas!$B$19 | D13: =80*Premissas!$B$31+10*Premissas!$B$30-Premissas!$B$19 | E13: =80*Premissas!$B$31+15*Premissas!$B$30-Premissas!$B$19 | F13: =80*Premissas!$B$31+20*Premissas!$B$30-Premissas!$B$19 | G13: =80*Premissas!$B$31+25*Premissas!$B$30-Premissas!$B$19 | H13: =80*Premissas!$B$31+30*Premissas!$B$30-Premissas!$B$19 | I13: =80*Premissas!$B$31+40*Premissas!$B$30-Premissas!$B$19 | J13: =80*Premissas!$B$31+50*Premissas!$B$30-Premissas!$B$19
A15: O sombreado é estático e foi calculado com as premissas atuais. Se você mudar preços ou custos, olhe o número, não a cor.

Sheet 5050 vs 20
A1: O 50/50 É MELHOR QUE A COMISSÃO DE 20%?
A2: No modelo de 20%, a Brand recebia 20% do faturamento e bancava o próprio time.
A3: No 50/50, custos e lucros são divididos — inclusive o tráfego.
A5: Faturamento bruto | B5: Você no 20% | C5: Você no 50/50 | D5: Diferença | E5: Melhor
A6: 20000 | B6: =A6*Premissas!$B$43-Premissas!$B$45 | C6: =(A6*(1-Premissas!$B$22)-(A6/Premissas!$B$36)*Premissas!$B$23-A6*(1-Premissas!$B$22)*Premissas!$B$24-Premissas!$B$19)*Premissas!$B$39 | D6: =C6-B6 | E6: =IF(C6>B6,"50/50","20%")
A7: 40000 | B7: =A7*Premissas!$B$43-Premissas!$B$45 | C7: =(A7*(1-Premissas!$B$22)-(A7/Premissas!$B$36)*Premissas!$B$23-A7*(1-Premissas!$B$22)*Premissas!$B$24-Premissas!$B$19)*Premissas!$B$39 | D7: =C7-B7 | E7: =IF(C7>B7,"50/50","20%")
A8: 60000 | B8: =A8*Premissas!$B$43-Premissas!$B$45 | C8: =(A8*(1-Premissas!$B$22)-(A8/Premissas!$B$36)*Premissas!$B$23-A8*(1-Premissas!$B$22)*Premissas!$B$24-Premissas!$B$19)*Premissas!$B$39 | D8: =C8-B8 | E8: =IF(C8>B8,"50/50","20%")
A9: 80000 | B9: =A9*Premissas!$B$43-Premissas!$B$45 | C9: =(A9*(1-Premissas!$B$22)-(A9/Premissas!$B$36)*Premissas!$B$23-A9*(1-Premissas!$B$22)*Premissas!$B$24-Premissas!$B$19)*Premissas!$B$39 | D9: =C9-B9 | E9: =IF(C9>B9,"50/50","20%")
A10: 100000 | B10: =A10*Premissas!$B$43-Premissas!$B$45 | C10: =(A10*(1-Premissas!$B$22)-(A10/Premissas!$B$36)*Premissas!$B$23-A10*(1-Premissas!$B$22)*Premissas!$B$24-Premissas!$B$19)*Premissas!$B$39 | D10: =C10-B10 | E10: =IF(C10>B10,"50/50","20%")
A11: 150000 | B11: =A11*Premissas!$B$43-Premissas!$B$45 | C11: =(A11*(1-Premissas!$B$22)-(A11/Premissas!$B$36)*Premissas!$B$23-A11*(1-Premissas!$B$22)*Premissas!$B$24-Premissas!$B$19)*Premissas!$B$39 | D11: =C11-B11 | E11: =IF(C11>B11,"50/50","20%")
A12: 200000 | B12: =A12*Premissas!$B$43-Premissas!$B$45 | C12: =(A12*(1-Premissas!$B$22)-(A12/Premissas!$B$36)*Premissas!$B$23-A12*(1-Premissas!$B$22)*Premissas!$B$24-Premissas!$B$19)*Premissas!$B$39 | D12: =C12-B12 | E12: =IF(C12>B12,"50/50","20%")
A13: 250000 | B13: =A13*Premissas!$B$43-Premissas!$B$45 | C13: =(A13*(1-Premissas!$B$22)-(A13/Premissas!$B$36)*Premissas!$B$23-A13*(1-Premissas!$B$22)*Premissas!$B$24-Premissas!$B$19)*Premissas!$B$39 | D13: =C13-B13 | E13: =IF(C13>B13,"50/50","20%")
A14: 300000 | B14: =A14*Premissas!$B$43-Premissas!$B$45 | C14: =(A14*(1-Premissas!$B$22)-(A14/Premissas!$B$36)*Premissas!$B$23-A14*(1-Premissas!$B$22)*Premissas!$B$24-Premissas!$B$19)*Premissas!$B$39 | D14: =C14-B14 | E14: =IF(C14>B14,"50/50","20%")
A16: Pior caso de cada modelo — se a campanha não vender nada:
A17: Você no 20% (só o seu time) | B17: =-Premissas!$B$45
A18: Você no 50/50 (metade de tudo) | B18: =-Premissas!$B$19*Premissas!$B$39
A19: Risco a mais que você assume | B19: =B18-B17
A21: A coluna do 50/50 ignora o imposto sobre faturamento, porque ele depende do regime e está zerado nas premissas.
